biostudiesclient/__init__.py
biostudiesclient/api.py
biostudiesclient/auth.py
biostudiesclient/config.py
biostudiesclient/exceptions.py
biostudiesclient/models.py
biostudiesclient/response_utils.py
biostudies_client-0.1.5.dist-info/LICENSE
biostudies_client-0.1.5.dist-info/METADATA
biostudies_client-0.1.5.dist-info/WHEEL
biostudies_client-0.1.5.dist-info/top_level.txt
biostudies_client-0.1.5.dist-info/RECORD
