Metadata-Version: 2.1
Name: biostudies-client
Version: 0.1.5
Summary: Python client library for wrapping and handling BioStudies REST API calls
Home-page: https://github.com/ebi-ait/biostudies-client
License: UNKNOWN
Platform: UNKNOWN
Classifier: Development Status :: 3 - Alpha
Classifier: Programming Language :: Python :: 3
Classifier: Operating System :: OS Independent
Requires-Dist: requests
